Metadata-Version: 2.1
Name: pylops-distributed
Version: 0.2.0
Summary: 
Home-page: UNKNOWN
Author: mrava
Author-email: mrava@equinor.com
License: UNKNOWN
Keywords: algebra,inverse problems,large-scale optimization
Platform: UNKNOWN
Classifier: Development Status :: 1 - Planning
Classifier: Intended Audience :: Developers
Classifier: Intended Audience :: Science/Research
Classifier: License :: OSI Approved :: GNU Lesser General Public License v3 or later (LGPLv3+)
Classifier: Natural Language :: English
Classifier: Programming Language :: Python :: 3.6
Classifier: Topic :: Scientific/Engineering :: Mathematics
Requires-Dist: numpy (>=1.15.0)
Requires-Dist: scipy
Requires-Dist: llvmlite
Requires-Dist: numba
Requires-Dist: dask[complete] (>=2.0.0)
Requires-Dist: pylops
